MANIFEST.in
requirements.txt
setup.py
pyl0n.egg-info/PKG-INFO
pyl0n.egg-info/SOURCES.txt
pyl0n.egg-info/dependency_links.txt
pyl0n.egg-info/requires.txt
pyl0n.egg-info/top_level.txt
pylon/__init__.py
pylon/nexus.py
pylon/probe.ini
pylon/beacons/__init__.py
pylon/beacons/beacon.py
pylon/beacons/cpu.py
pylon/beacons/disk.py
pylon/beacons/memory.py
pylon/beacons/network.py