Metadata-Version: 1.1
Name: pyl0n
Version: 0.0.7
Summary: Use psutils to send data to Graphite Backend
Home-page: https://github.com/padajuan/pylon
Author: Juan Manuel Parrilla Madrid
Author-email: padajuan@gmail.com
License: GPLv2
Keywords: psutil pylon monitoring graphite
Platform: UNKNOWN
Classifier: Development Status :: 3 - Alpha
Classifier: Environment :: Console
Classifier: Intended Audience :: Developers
Classifier: Intended Audience :: System Administrators
Classifier: License :: OSI Approved :: GNU General Public License v2 (GPLv2)
Classifier: Operating System :: POSIX :: Linux
Classifier: Topic :: System :: Monitoring
Classifier: Topic :: System :: Operating System
